Control/Control.v
module Control(	input wire clk,
				input wire rst,
				output reg [2:0] command_1 = 3'b0,
				output reg start,
				input wire ready_command);

reg [24:0] timer;

//Parametros maquina de estados
localparam S_INIT		=  	3'b000;
localparam S_SEND 		= 	3'b001;
localparam S_WAITCOM 	= 	3'b010;
localparam S_TIMER 		= 	3'b100;

reg [2:0] state = S_INIT;

always @(posedge clk or posedge rst) begin
	if (!rst) begin
		state = S_INIT;
	end else begin
		case(state)
			S_INIT: begin
				timer = 25'd5;
				start = 1'b1;
				state = S_SEND;
			end
			S_SEND: begin
				if(ready_command==1'b1)begin
					state = S_SEND;
				end else begin
					state = S_WAITCOM;
				end
			end
			S_WAITCOM: begin
					if(ready_command == 1'b0) begin
						state = S_WAITCOM;
					end else begin
						state = S_TIMER;
					end		
			end
			S_TIMER: begin
				if(timer>0)begin
					timer = timer - 25'd1;
					state = S_TIMER;
				end else begin
					command_1 = command_1 + 1;
					state = S_INIT;
				end
			end
			default: begin
				state = S_INIT;
			end
		endcase
	end
end

endmodule

Control/Control_TB.v
`timescale 10ns / 10ps
`define SIMULATION

module Control_TB;
    reg clk = 1'b0, rst, ready_command;
    wire command_1;

    Control 
        inst1(clk, rst, command_1, start, ready_command);

    always #1 clk = ~clk; 

    initial begin
        #1000000
        $finish;
    end

    initial begin
    rst = 1'b0;
    #10
    ready_command = 1'b0;
    end

   initial begin
     $dumpfile("Control_TB.vcd");
     $dumpvars(-1, inst1);
   end

endmodule

Control/simulation/Control_TB.vcd
$date
	Fri Oct 28 14:16:06 2016
$end
$version
	Icarus Verilog
$end
$timescale
	10ps
$end
$scope module Control_TB $end
$scope module inst1 $end
$var wire 1 ! clk $end
$var wire 1 " ready_command $end
$var wire 1 # rst $end
$var reg 3 $ command_1 [2:0] $end
$var reg 1 % start $end
$var reg 3 & state [2:0] $end
$var reg 25 ' timer [24:0] $end
$upscope $end
$upscope $end
$enddefinitions $end
#0
$dumpvars
b101 '
b1 &
1%
b0 $
1#
1"
0!
$end
#1000
1!
#2000
0!
#3000
1!
#4000
0!
#5000
1!
#6000
0!
#7000
1!
#8000
0!
#9000
1!
#10000
0!
0"
#11000
b10 &
1!
#12000
0!
#13000
1!
#14000
0!
#15000
1!
#16000
0!
#17000
1!
#18000
0!
#19000
1!
#20000
0!
#21000
1!
#22000
0!
#23000
1!
#24000
0!
#25000
1!
#26000
0!
#27000
1!
#28000
0!
#29000
1!
#30000
0!
#31000
1!
#32000
0!
#33000
1!
#34000
0!
#35000
1!
#36000
0!
#37000
1!
#38000
0!
#39000
1!
#40000
0!
1"
#41000
b100 &
1!
#42000
0!
#43000
b100 '
1!
#44000
0!
#45000
b11 '
1!
#46000
0!
#47000
b10 '
1!
#48000
0!
#49000
b1 '
1!
#50000
0!
0"
#51000
b0 '
1!
#52000
0!
#53000
b0 &
b1 $
1!
#54000
0!
#55000
b1 &
b101 '
1!
#56000
0!
#57000
b10 &
1!
#58000
0!
#59000
1!
#60000
0!
#61000
1!
#62000
0!
#63000
1!
#64000
0!
#65000
1!
#66000
0!
#67000
1!
#68000
0!
#69000
1!
#70000
0!
#71000
1!
#72000
0!
#73000
1!
#74000
0!
#75000
1!
#76000
0!
#77000
1!
#78000
0!
#79000
1!
#80000
0!
1"
#81000
b100 &
1!
#82000
0!
#83000
b100 '
1!
#84000
0!
#85000
b11 '
1!
#86000
0!
#87000
b10 '
1!
#88000
0!
#89000
b1 '
1!
#90000
0!
0"
#91000
b0 '
1!
#92000
0!
#93000
b0 &
b10 $
1!
#94000
0!
#95000
b1 &
b101 '
1!
#96000
0!
#97000
b10 &
1!
#98000
0!
#99000
1!
#100000
0!
#101000
1!
#102000
0!
#103000
1!
#104000
0!
#105000
1!
#106000
0!
#107000
1!
#108000
0!
#109000
1!
#110000
0!
#111000
1!
#112000
0!
#113000
1!
#114000
0!
#115000
1!
#116000
0!
#117000
1!
#118000
0!
#119000
1!
#120000
0!
1"
#121000
b100 &
1!
#122000
0!
#123000
b100 '
1!
#124000
0!
#125000
b11 '
1!
#126000
0!
#127000
b10 '
1!
#128000
0!
#129000
b1 '
1!
#130000
0!
0"
#131000
b0 '
1!
#132000
0!
#133000
b0 &
b11 $
1!
#134000
0!
#135000
b1 &
b101 '
1!
#136000
0!
#137000
b10 &
1!
#138000
0!
#139000
1!
#140000
0!
#141000
1!
#142000
0!
#143000
1!
#144000
0!
#145000
1!
#146000
0!
#147000
1!
#148000
0!
#149000
1!
#150000
0!
#151000
1!
#152000
0!
#153000
1!
#154000
0!
#155000
1!
#156000
0!
#157000
1!
#158000
0!
#159000
1!
#160000
0!
1"
#161000
b100 &
1!
#162000
0!
#163000
b100 '
1!
#164000
0!
#165000
b11 '
1!
#166000
0!
#167000
b10 '
1!
#168000
0!
#169000
b1 '
1!
#170000
0!
0"
#171000
b0 '
1!
#172000
0!
#173000
b0 &
b100 $
1!
#174000
0!
#175000
b1 &
b101 '
1!
#176000
0!
#177000
b10 &
1!
#178000
0!
#179000
1!
#180000
0!
#181000
1!
#182000
0!
#183000
1!
#184000
0!
#185000
1!
#186000
0!
#187000
1!
#188000
0!
#189000
1!
#190000
0!
#191000
1!
#192000
0!
#193000
1!
#194000
0!
#195000
1!
#196000
0!
#197000
1!
#198000
0!
#199000
1!
#200000
0!
1"
#201000
b100 &
1!
#202000
0!
#203000
b100 '
1!
#204000
0!
#205000
b11 '
1!
#206000
0!
#207000
b10 '
1!
#208000
0!
#209000
b1 '
1!
#210000
0!
#211000
b0 '
1!
#212000
0!
#213000
b0 &
b101 $
1!
#214000
0!
#215000
b1 &
b101 '
1!
