baudgen.vh
//-- Fichero baudgen.vh

// 12MHz External Clock
//`define B115200 104
//`define B57600  208
//`define B38400  313
//`define B19200  625
//`define B9600   1250
//`define B4800   2500
//`define B2400   5000
//`define B1200   10000
//`define B600    20000
//`define B300    40000

// 50MHz External Clock
`define B115200 434
`define B57600  868
`define B38400  1302
`define B19200  2604
`define B9600   5208
`define B4800   10417
`define B2400   20833
`define B1200   41667
`define B600    83333
`define B300    166667

// 100MHz External Clock
//`define B115200 868
//`define B57600  1736
//`define B38400  2604
//`define B19200  5208
//`define B9600   10417
//`define B4800   20833
//`define B2400   41667
//`define B1200   83333
//`define B600    166667
//`define B300    333333


//Test
`define B008    2

baudgen.v
//-----------------------------------------------------------------------------
//-- Generacion de baudios
//-- Señal cuadrada, de periodo igual a la frecuencia de los baudios indicados
//-- El ancho del pulso positivo es de 1 ciclo de reloj
//--
//-- (c) BQ. August 2015. written by Juan Gonzalez (obijuan)
//-----------------------------------------------------------------------------
//-- GPL license
//-----------------------------------------------------------------------------
`include "baudgen.vh"

`define log2(n)   ((n) <= (1<<0)  ? 0 : (n)  <= (1<<1)  ? 1  :\
                   (n) <= (1<<2)  ? 2 : (n)  <= (1<<3)  ? 3  :\
                   (n) <= (1<<4)  ? 4 : (n)  <= (1<<5)  ? 5  :\
                   (n) <= (1<<6)  ? 6 : (n)  <= (1<<7)  ? 7  :\
                   (n) <= (1<<8)  ? 8 : (n)  <= (1<<9)  ? 9  :\
                   (n) <= (1<<10) ? 10 : (n) <= (1<<11) ? 11 :\
                   (n) <= (1<<12) ? 12 : (n) <= (1<<13) ? 13 :\
                   (n) <= (1<<14) ? 14 : (n) <= (1<<15) ? 15 :\
                   (n) <= (1<<16) ? 16 : (n) <= (1<<17) ? 17 :\
                   (n) <= (1<<18) ? 18 : (n) <= (1<<19) ? 19 :\
                   (n) <= (1<<20) ? 20 : (n) <= (1<<21) ? 21 :\
                   (n) <= (1<<22) ? 22 : (n) <= (1<<23) ? 23 :\
                   (n) <= (1<<24) ? 24 : (n) <= (1<<25) ? 25 :\
                   (n) <= (1<<26) ? 26 : (n) <= (1<<27) ? 27 :\
                   (n) <= (1<<28) ? 28 : (n) <= (1<<29) ? 29 :\
                   (n) <= (1<<30) ? 30 : (n) <= (1<<31) ? 31 : 32)

//-- ENTRADAS:
//--     -clk: Senal de reloj del sistema (12 MHZ en la iceStick)
//--     -clk_ena: Habilitacion. 
//--            1. funcionamiento normal. Emitiendo pulsos
//--            0: Inicializado y parado. No se emiten pulsos
//
//-- SALIDAS:
//--     - clk_out. Señal de salida para lograr la velocidad en baudios indicada
//--                Anchura de 1 periodo de clk. SALIDA NO REGISTRADA
module baudgen(input wire clk,
               input wire clk_ena, 
               output wire clk_out);

//-- Valor por defecto de la velocidad en baudios
parameter M = `B115200;

//-- Numero de bits para almacenar el divisor de baudios
//localparam N = $clog2(M); 
localparam N = `log2(M);

//-- Registro para implementar el contador modulo M
reg [N-1:0] divcounter = 0;

//-- Contador módulo M
always @(posedge clk)

  if (clk_ena)
    //-- Funcionamiento normal
    divcounter <= (divcounter == M - 1) ? 0 : divcounter + 1;
  else
    //-- Contador "congelado" al valor maximo
    divcounter <= M - 1;

//-- Sacar un pulso de anchura 1 ciclo de reloj si el generador
//-- esta habilitado (clk_ena == 1)
//-- en caso contrario se saca 0
assign clk_out = (divcounter == 0) ? clk_ena : 0;


endmodule

Comunicaciones/uart_tx.v
//-- Fichero: uart_tx.v
`default_nettype none

// 50MHz External Clock
`define B115200 434
`define B57600  868
`define B38400  1302
`define B19200  2604
`define B9600   5208
`define B4800   10417
`define B2400   20833
`define B1200   41667
`define B600    83333
`define B300    166667

//--- Modulo de transmision serie
//--- La salida tx ESTA REGISTRADA
module uart_tx (
         input wire clk,        //-- Reloj del sistema (12MHz en ICEstick)
         input wire rstn,       //-- Reset global (activo nivel bajo)
         input wire start,      //-- Activar a 1 para transmitir
         input wire [7:0] data, //-- Byte a transmitir
         output reg tx,         //-- Salida de datos serie (hacia el PC)
         output wire ready      //-- Transmisor listo / ocupado
       );

//-- Parametro: velocidad de transmision
parameter BAUD =  `B115200;

//-- Señal de start registrada
reg start_r; 

//-- Reloj para la transmision
wire clk_baud;

//-- Bitcounter
reg [3:0] bitc;

//-- Datos registrados
reg [7:0] data_r;

//--------- Microordenes
wire load;    //-- Carga del registro de desplazamiento. Puesta a 0 del
              //-- contador de bits
wire baud_en; //-- Habilitar el generador de baudios para la transmision

//-- Registro de 10 bits para almacenar la trama a enviar:
//-- 1 bit start + 8 bits datos + 1 bit stop
reg [9:0] shifter;

//-- Estados del automata finito del controlador
localparam IDLE  = 0;  //-- Estado de reposo
localparam START = 1;  //-- Comienzo de transmision
localparam TRANS = 2;  //-- Estado: transmitiendo dato

//-- Estados del autómata del controlador
reg [1:0] state;

//-------------------------------------
//-- RUTA DE DATOS
//-------------------------------------

//-- Registrar la entrada start
//-- (para cumplir con las reglas de diseño sincrono)
always @(posedge clk)
  start_r <= start;

always @(posedge clk)
  if (start == 1 && state == IDLE)
    data_r <= data;



//-- Cuando la microorden load es 1 se carga la trama
//-- con load 0 se desplaza a la derecha y se envia un bit, al
//-- activarse la señal de clk_baud que marca el tiempo de bit
//-- Se introducen 1s por la izquierda
always @(posedge clk)
  //-- Reset
  if (rstn == 0)
    shifter <= 10'b11_1111_1111;

  //-- Modo carga
  else if (load == 1)
    shifter <= {data_r,2'b01};

  //-- Modo desplazamiento
  else if (load == 0 && clk_baud == 1)
    shifter <= {1'b1, shifter[9:1]};

//-- Contador de bits enviados
//-- Con la microorden load (=1) se hace un reset del contador
//-- con load = 0 se realiza la cuenta de los bits, al activarse
//-- clk_baud, que indica el tiempo de bit
always @(posedge clk)
  if (load == 1)
    bitc <= 0;
  else if (load == 0 && clk_baud == 1)
    bitc <= bitc + 1;

//-- Sacar por tx el bit menos significativo del registros de desplazamiento
//-- ES UNA SALIDA REGISTRADA, puesto que tx se conecta a un bus sincrono
//-- y hay que evitar que salgan pulsos espureos (glitches)
always @(posedge clk)
  tx <= shifter[0];

//-- Divisor para obtener el reloj de transmision
baudgen #(BAUD)
  BAUD0 (
    .clk(clk),
    .clk_ena(baud_en),
    .clk_out(clk_baud)
  );

//------------------------------
//-- CONTROLADOR
//------------------------------

//-- Transiciones entre los estados
always @(posedge clk)

  //-- Reset del automata. Al estado inicial
  if (rstn == 0)
    state <= IDLE;

  else
    //-- Transiciones a los siguientes estados
    case (state)

      //-- Estado de reposo. Se sale cuando la señal
      //-- de start se pone a 1
      IDLE: 
        if (start_r == 1) 
          state <= START;
        else 
          state <= IDLE;

      //-- Estado de comienzo. Prepararse para empezar
      //-- a transmitir. Duracion: 1 ciclo de reloj
      START:
        state <= TRANS;

      //-- Transmitiendo. Se esta en este estado hasta
      //-- que se hayan transmitido todos los bits pendientes
      TRANS:
        if (bitc == 11)
          state <= IDLE;
        else
          state <= TRANS;

      //-- Por defecto. NO USADO. Puesto para
      //-- cubrir todos los casos y que no se generen latches
      default:
        state <= IDLE;

    endcase

//-- Generacion de las microordenes
assign load = (state == START) ? 1 : 0;
assign baud_en = (state == IDLE) ? 0 : 1;

//-- Señal de salida. Esta a 1 cuando estamos en reposo (listos
//-- para transmitir). En caso contrario esta a 0
assign ready = (state == IDLE) ? 1 : 0;

endmodule

EnviarDatos/EnviarDatos.v
`define B115200 434
`define B57600  868
`define B38400  1302
`define B19200  2604
`define B9600   5208
`define B4800   10417
`define B2400   20833
`define B1200   41667
`define B600    83333
`define B300    166667

module EnviarDatos(	input wire clk,
					input wire rst,
					input wire start,
					input wire [7:0] datos,
					output wire tx
					);

//Velocidad de transmision
	parameter BAUD 			= `B115200;
	reg start_uart 			= 1'b0;
	reg [2:0] state 		= INIT;
	wire [7:0] data_send;
	wire ready_u;
	reg [27:0] timer		= 28'd0;
	reg [7:0] numeros 		= 8'h30;

assign data_send = numeros;
//Instanciar UART
uart_tx #(.BAUD(BAUD))
	  TX0 (
	    .clk(clk), //Señal de reloj matrix
	    .rstn(rst), //Reset del protocolo
	    .data(data_send), //Datos a enviar
	    .start(start_uart),  // Activar a 1 para transmitir
	    .ready(ready_u), // 1 para reposo (Listos para transmitir) 0 para acabar
	    .tx(tx) //-- Salida de datos serie (hacia el PC)
	  );

	localparam INIT 	= 		3'b000;
	localparam WAIT		=		3'b001;
	localparam SEND 	= 		3'b010;
	localparam STOP 	= 		3'b100;

	


always @(posedge clk or negedge rst) begin
	if (!rst) begin
	state = INIT;
	end else begin
		case(state)
				INIT: begin
					if(start==1'b1)begin
					timer 		= 28'd25000000;
					state		= WAIT;
					start_uart 	= 1'b0;
				end else begin
						state = INIT;
						start_uart = 1'b0;
					end
				end
				WAIT:begin
					if(ready_u==0)begin
						state = WAIT;
					end else begin
						state = SEND;
					end
				end
				SEND: begin
					if(timer>0)begin
						timer 		= timer - 28'd1;
					end else begin
						if(numeros == 8'h39)begin
							state	= STOP;
						end else begin
							start_uart 	= 1'b1;
							numeros 	= numeros + 8'd1;
							state 		= INIT;	
						end
					end
				end
				STOP:begin
					start_uart	= 1'b0;
				end					
				default:begin
					state 		= INIT;
					start_uart	= 1'b0;
					numeros 	= 8'd0; 
				end
		endcase
	end
end
endmodule

EnviarDatos/EnviarDatos_TB.v
`timescale 10ns / 10ps
`define SIMULATION

module EnviarDatos_TB;
    reg clk = 1'b0;
    wire tx;
    reg rst;
    reg start;
    reg [7:0] datos;
    wire [7:0] data_send;
    reg [7:0] numeros;

    EnviarDatos 
        inst1(clk, rst, start, datos, tx);

    always #1 clk = ~clk; 

    initial begin
        #100000
        $finish;
    end

    initial begin
    rst = 1'b1;
    numeros = 8'd1;
    #10
    start = 1'b1;
    end

   initial begin
     $dumpfile("EnviarDatos_TB.vcd");
     $dumpvars(-1, inst1);
   end

endmodule

EnviarDatos/simulation/EnviarDatos_TB.vcd
$date
	Thu Nov  3 10:34:40 2016
$end
$version
	Icarus Verilog
$end
$timescale
	10ps
$end
$scope module EnviarDatos_TB $end
$scope module inst1 $end
$var wire 1 ! clk $end
$var wire 8 " data_send [7:0] $end
$var wire 8 # datos [7:0] $end
$var wire 1 $ ready_u $end
$var wire 1 % rst $end
$var wire 1 & start $end
$var wire 1 ' tx $end
$var reg 8 ( numeros [7:0] $end
$var reg 1 ) start_uart $end
$var reg 3 * state [2:0] $end
$var reg 28 + timer [27:0] $end
$scope module TX0 $end
$var wire 1 , baud_en $end
$var wire 1 ! clk $end
$var wire 1 - clk_baud $end
$var wire 8 . data [7:0] $end
$var wire 1 / load $end
$var wire 1 $ ready $end
$var wire 1 % rstn $end
$var wire 1 0 start $end
$var reg 4 1 bitc [3:0] $end
$var reg 8 2 data_r [7:0] $end
$var reg 10 3 shifter [9:0] $end
$var reg 1 4 start_r $end
$var reg 2 5 state [1:0] $end
$var reg 1 6 tx $end
$scope module BAUD0 $end
$var wire 1 ! clk $end
$var wire 1 , clk_ena $end
$var wire 1 - clk_out $end
$var reg 9 7 divcounter [8:0] $end
$upscope $end
$upscope $end
$upscope $end
$upscope $end
$enddefinitions $end
#0
$dumpvars
b0 7
x6
bx 5
x4
bx 3
bx 2
bx 1
00
x/
b0 .
x-
x,
b0 +
b0 *
0)
b0 (
x'
x&
1%
x$
bx #
b0 "
0!
$end
#1000
0-
0/
0,
1$
b110110001 7
04
b0 5
1!
#2000
0!
#3000
1!
#4000
0!
#5000
1!
#6000
0!
#7000
1!
#8000
0!
#9000
1!
#10000
0!
1&
#11000
b0 2
14
b1 *
1)
10
b1010 +
1!
#12000
0!
#13000
1/
1,
0$
b1 5
b10 *
1!
#14000
0!
#15000
0/
1-
b10 5
b0 1
b1 3
b0 7
b1001 +
1!
#16000
0!
#17000
0-
b1 7
b1000000000 3
b1 1
16
1'
b1000 +
1!
#18000
0!
#19000
06
0'
b10 7
b111 +
1!
#20000
0!
#21000
b11 7
b110 +
1!
#22000
0!
#23000
b100 7
b101 +
1!
#24000
0!
#25000
b101 7
b100 +
1!
#26000
0!
#27000
b110 7
b11 +
1!
#28000
0!
#29000
b111 7
b10 +
1!
#30000
0!
#31000
b1000 7
b1 +
1!
#32000
0!
#33000
b1001 7
b0 +
1!
#34000
0!
#35000
04
b1010 7
b0 *
b1 (
b1 "
b1 .
0)
00
1!
#36000
0!
#37000
b1011 7
14
b1 *
1)
10
b1010 +
1!
#38000
0!
#39000
b1100 7
1!
#40000
0!
#41000
b1101 7
1!
#42000
0!
#43000
b1110 7
1!
#44000
0!
#45000
b1111 7
1!
#46000
0!
#47000
b10000 7
1!
#48000
0!
#49000
b10001 7
1!
#50000
0!
#51000
b10010 7
1!
#52000
0!
#53000
b10011 7
1!
#54000
0!
#55000
b10100 7
1!
#56000
0!
#57000
b10101 7
1!
#58000
0!
#59000
b10110 7
1!
#60000
0!
#61000
b10111 7
1!
#62000
0!
#63000
b11000 7
1!
#64000
0!
#65000
b11001 7
1!
#66000
0!
#67000
b11010 7
1!
#68000
0!
#69000
b11011 7
1!
#70000
0!
#71000
b11100 7
1!
#72000
0!
#73000
b11101 7
1!
#74000
0!
#75000
b11110 7
1!
#76000
0!
#77000
b11111 7
1!
#78000
0!
#79000
b100000 7
1!
#80000
0!
#81000
b100001 7
1!
#82000
0!
#83000
b100010 7
1!
#84000
0!
#85000
b100011 7
1!
#86000
0!
#87000
b100100 7
1!
#88000
0!
#89000
b100101 7
1!
#90000
0!
#91000
b100110 7
1!
#92000
0!
#93000
b100111 7
1!
#94000
0!
#95000
b101000 7
1!
#96000
0!
#97000
b101001 7
1!
#98000
0!
#99000
b101010 7
1!
#100000
0!
#101000
b101011 7
1!
#102000
0!
#103000
b101100 7
1!
#104000
0!
#105000
b101101 7
1!
#106000
0!
#107000
b101110 7
1!
#108000
0!
#109000
b101111 7
1!
#110000
0!
#111000
b110000 7
1!
#112000
0!
#113000
b110001 7
1!
#114000
0!
#115000
b110010 7
1!
#116000
0!
#117000
b110011 7
1!
#118000
0!
#119000
b110100 7
1!
#120000
0!
#121000
b110101 7
1!
#122000
0!
#123000
b110110 7
1!
#124000
0!
#125000
b110111 7
1!
#126000
0!
#127000
b111000 7
1!
#128000
0!
#129000
b111001 7
1!
#130000
0!
#131000
b111010 7
1!
#132000
0!
#133000
b111011 7
1!
#134000
0!
#135000
b111100 7
1!
#136000
0!
#137000
b111101 7
1!
#138000
0!
#139000
b111110 7
1!
#140000
0!
#141000
b111111 7
1!
#142000
0!
#143000
b1000000 7
1!
#144000
0!
#145000
b1000001 7
1!
#146000
0!
#147000
b1000010 7
1!
#148000
0!
#149000
b1000011 7
1!
#150000
0!
#151000
b1000100 7
1!
#152000
0!
#153000
b1000101 7
1!
#154000
0!
#155000
b1000110 7
1!
#156000
0!
#157000
b1000111 7
1!
#158000
0!
#159000
b1001000 7
1!
#160000
0!
#161000
b1001001 7
1!
#162000
0!
#163000
b1001010 7
1!
#164000
0!
#165000
b1001011 7
1!
#166000
0!
#167000
b1001100 7
1!
#168000
0!
#169000
b1001101 7
1!
#170000
0!
#171000
b1001110 7
1!
#172000
0!
#173000
b1001111 7
1!
#174000
0!
#175000
b1010000 7
1!
#176000
0!
#177000
b1010001 7
1!
#178000
0!
#179000
b1010010 7
1!
#180000
0!
#181000
b1010011 7
1!
#182000
0!
#183000
b1010100 7
1!
#184000
0!
#185000
b1010101 7
1!
#186000
0!
#187000
b1010110 7
1!
#188000
0!
#189000
b1010111 7
1!
#190000
0!
#191000
b1011000 7
1!
#192000
0!
#193000
b1011001 7
1!
#194000
0!
#195000
b1011010 7
1!
#196000
0!
#197000
b1011011 7
1!
#198000
0!
#199000
b1011100 7
1!
#200000
0!
#201000
b1011101 7
1!
#202000
0!
#203000
b1011110 7
1!
#204000
0!
#205000
b1011111 7
1!
#206000
0!
#207000
b1100000 7
1!
#208000
0!
#209000
b1100001 7
1!
#210000
0!
#211000
b1100010 7
1!
#212000
0!
#213000
b1100011 7
1!
#214000
0!
#215000
b1100100 7
1!
#216000
0!
#217000
b1100101 7
1!
#218000
0!
#219000
b1100110 7
1!
#220000
0!
#221000
b1100111 7
1!
#222000
0!
#223000
b1101000 7
1!
#224000
0!
#225000
b1101001 7
1!
#226000
0!
#227000
b1101010 7
1!
#228000
0!
#229000
b1101011 7
1!
#230000
0!
#231000
b1101100 7
1!
#232000
0!
#233000
b1101101 7
1!
#234000
0!
#235000
b1101110 7
1!
#236000
0!
#237000
b1101111 7
1!
#238000
0!
#239000
b1110000 7
1!
#240000
0!
#241000
b1110001 7
1!
#242000
0!
#243000
b1110010 7
1!
#244000
0!
#245000
b1110011 7
1!
#246000
0!
#247000
b1110100 7
1!
#248000
0!
#249000
b1110101 7
1!
#250000
0!
#251000
b1110110 7
1!
#252000
0!
#253000
b1110111 7
1!
#254000
0!
#255000
b1111000 7
1!
#256000
0!
#257000
b1111001 7
1!
#258000
0!
#259000
b1111010 7
1!
#260000
0!
#261000
b1111011 7
1!
#262000
0!
#263000
b1111100 7
1!
#264000
0!
#265000
b1111101 7
1!
#266000
0!
#267000
b1111110 7
1!
#268000
0!
#269000
b1111111 7
1!
#270000
0!
#271000
b10000000 7
1!
#272000
0!
#273000
b10000001 7
1!
#274000
0!
#275000
b10000010 7
1!
#276000
0!
#277000
b10000011 7
1!
#278000
0!
#279000
b10000100 7
1!
#280000
0!
#281000
b10000101 7
1!
#282000
0!
#283000
b10000110 7
1!
#284000
0!
#285000
b10000111 7
1!
#286000
0!
#287000
b10001000 7
1!
#288000
0!
#289000
b10001001 7
1!
#290000
0!
#291000
b10001010 7
1!
#292000
0!
#293000
b10001011 7
1!
#294000
0!
#295000
b10001100 7
1!
#296000
0!
#297000
b10001101 7
1!
#298000
0!
#299000
b10001110 7
1!
#300000
0!
#301000
b10001111 7
1!
#302000
0!
#303000
b10010000 7
1!
#304000
0!
#305000
b10010001 7
1!
#306000
0!
#307000
b10010010 7
1!
#308000
0!
#309000
b10010011 7
1!
#310000
0!
#311000
b10010100 7
1!
#312000
0!
#313000
b10010101 7
1!
#314000
0!
#315000
b10010110 7
1!
#316000
0!
#317000
b10010111 7
1!
#318000
0!
#319000
b10011000 7
1!
#320000
0!
#321000
b10011001 7
1!
#322000
0!
#323000
b10011010 7
1!
#324000
0!
#325000
b10011011 7
1!
#326000
0!
#327000
b10011100 7
1!
#328000
0!
#329000
b10011101 7
1!
#330000
0!
#331000
b10011110 7
1!
#332000
0!
#333000
b10011111 7
1!
#334000
0!
#335000
b10100000 7
1!
#336000
0!
#337000
b10100001 7
1!
#338000
0!
#339000
b10100010 7
1!
#340000
0!
#341000
b10100011 7
1!
#342000
0!
#343000
b10100100 7
1!
#344000
0!
#345000
b10100101 7
1!
#346000
0!
#347000
b10100110 7
1!
#348000
0!
#349000
b10100111 7
1!
#350000
0!
#351000
b10101000 7
1!
#352000
0!
#353000
b10101001 7
1!
#354000
0!
#355000
b10101010 7
1!
#356000
0!
#357000
b10101011 7
1!
#358000
0!
#359000
b10101100 7
1!
#360000
0!
#361000
b10101101 7
1!
#362000
0!
#363000
b10101110 7
1!
#364000
0!
#365000
b10101111 7
1!
#366000
0!
#367000
b10110000 7
1!
#368000
0!
#369000
b10110001 7
1!
#370000
0!
#371000
b10110010 7
1!
#372000
0!
#373000
b10110011 7
1!
#374000
0!
#375000
b10110100 7
1!
#376000
0!
#377000
b10110101 7
1!
#378000
0!
#379000
b10110110 7
1!
#380000
0!
#381000
b10110111 7
1!
#382000
0!
#383000
b10111000 7
1!
#384000
0!
#385000
b10111001 7
1!
#386000
0!
#387000
b10111010 7
1!
#388000
0!
#389000
b10111011 7
1!
#390000
0!
#391000
b10111100 7
1!
#392000
0!
#393000
b10111101 7
1!
#394000
0!
#395000
b10111110 7
1!
#396000
0!
#397000
b10111111 7
1!
#398000
0!
#399000
b11000000 7
1!
#400000
0!
#401000
b11000001 7
1!
#402000
0!
#403000
b11000010 7
1!
#404000
0!
#405000
b11000011 7
1!
#406000
0!
#407000
b11000100 7
1!
#408000
0!
#409000
b11000101 7
1!
#410000
0!
#411000
b11000110 7
1!
#412000
0!
#413000
b11000111 7
1!
#414000
0!
#415000
b11001000 7
1!
#416000
0!
#417000
b11001001 7
1!
#418000
0!
#419000
b11001010 7
1!
#420000
0!
#421000
b11001011 7
1!
#422000
0!
#423000
b11001100 7
1!
#424000
0!
#425000
b11001101 7
1!
#426000
0!
#427000
b11001110 7
1!
#428000
0!
#429000
b11001111 7
1!
#430000
0!
#431000
b11010000 7
1!
#432000
0!
#433000
b11010001 7
1!
#434000
0!
#435000
b11010010 7
1!
#436000
0!
#437000
b11010011 7
1!
#438000
0!
#439000
b11010100 7
1!
#440000
0!
#441000
b11010101 7
1!
#442000
0!
#443000
b11010110 7
1!
#444000
0!
#445000
b11010111 7
1!
#446000
0!
#447000
b11011000 7
1!
#448000
0!
#449000
b11011001 7
1!
#450000
0!
#451000
b11011010 7
1!
#452000
0!
#453000
b11011011 7
1!
#454000
0!
#455000
b11011100 7
1!
#456000
0!
#457000
b11011101 7
1!
#458000
0!
#459000
b11011110 7
1!
#460000
0!
#461000
b11011111 7
1!
#462000
0!
#463000
b11100000 7
1!
#464000
0!
#465000
b11100001 7
1!
#466000
0!
#467000
b11100010 7
1!
#468000
0!
#469000
b11100011 7
1!
#470000
0!
#471000
b11100100 7
1!
#472000
0!
#473000
b11100101 7
1!
#474000
0!
#475000
b11100110 7
1!
#476000
0!
#477000
b11100111 7
1!
#478000
0!
#479000
b11101000 7
1!
#480000
0!
#481000
b11101001 7
1!
#482000
0!
#483000
b11101010 7
1!
#484000
0!
#485000
b11101011 7
1!
#486000
0!
#487000
b11101100 7
1!
#488000
0!
#489000
b11101101 7
1!
#490000
0!
#491000
b11101110 7
1!
#492000
0!
#493000
b11101111 7
1!
#494000
0!
#495000
b11110000 7
1!
#496000
0!
#497000
b11110001 7
1!
#498000
0!
#499000
b11110010 7
1!
#500000
0!
#501000
b11110011 7
1!
#502000
0!
#503000
b11110100 7
1!
#504000
0!
#505000
b11110101 7
1!
#506000
0!
#507000
b11110110 7
1!
#508000
0!
#509000
b11110111 7
1!
#510000
0!
#511000
b11111000 7
1!
#512000
0!
#513000
b11111001 7
1!
#514000
0!
#515000
b11111010 7
1!
#516000
0!
#517000
b11111011 7
1!
#518000
0!
#519000
b11111100 7
1!
#520000
0!
#521000
b11111101 7
1!
#522000
0!
#523000
b11111110 7
1!
#524000
0!
#525000
b11111111 7
1!
#526000
0!
#527000
b100000000 7
1!
#528000
0!
#529000
b100000001 7
1!
#530000
0!
#531000
b100000010 7
1!
#532000
0!
#533000
b100000011 7
1!
#534000
0!
#535000
b100000100 7
1!
#536000
0!
#537000
b100000101 7
1!
#538000
0!
#539000
b100000110 7
1!
#540000
0!
#541000
b100000111 7
1!
#542000
0!
#543000
b100001000 7
1!
#544000
0!
#545000
b100001001 7
1!
#546000
0!
#547000
b100001010 7
1!
#548000
0!
#549000
b100001011 7
1!
#550000
0!
#551000
b100001100 7
1!
#552000
0!
#553000
b100001101 7
1!
#554000
0!
#555000
b100001110 7
1!
#556000
0!
#557000
b100001111 7
1!
#558000
0!
#559000
b100010000 7
1!
#560000
0!
#561000
b100010001 7
1!
#562000
0!
#563000
b100010010 7
1!
#564000
0!
#565000
b100010011 7
1!
#566000
0!
#567000
b100010100 7
1!
#568000
0!
#569000
b100010101 7
1!
#570000
0!
#571000
b100010110 7
1!
#572000
0!
#573000
b100010111 7
1!
#574000
0!
#575000
b100011000 7
1!
#576000
0!
#577000
b100011001 7
1!
#578000
0!
#579000
b100011010 7
1!
#580000
0!
#581000
b100011011 7
1!
#582000
0!
#583000
b100011100 7
1!
#584000
0!
#585000
b100011101 7
1!
#586000
0!
#587000
b100011110 7
1!
#588000
0!
#589000
b100011111 7
1!
#590000
0!
#591000
b100100000 7
1!
#592000
0!
#593000
b100100001 7
1!
#594000
0!
#595000
b100100010 7
1!
#596000
0!
#597000
b100100011 7
1!
#598000
0!
#599000
b100100100 7
1!
#600000
0!
#601000
b100100101 7
1!
#602000
0!
#603000
b100100110 7
1!
#604000
0!
#605000
b100100111 7
1!
#606000
0!
#607000
b100101000 7
1!
#608000
0!
#609000
b100101001 7
1!
#610000
0!
#611000
b100101010 7
1!
#612000
0!
#613000
b100101011 7
1!
#614000
0!
#615000
b100101100 7
1!
#616000
0!
#617000
b100101101 7
1!
#618000
0!
#619000
b100101110 7
1!
#620000
0!
#621000
b100101111 7
1!
#622000
0!
#623000
b100110000 7
1!
#624000
0!
#625000
b100110001 7
1!
#626000
0!
#627000
b100110010 7
1!
#628000
0!
#629000
b100110011 7
1!
#630000
0!
#631000
b100110100 7
1!
#632000
0!
#633000
b100110101 7
1!
#634000
0!
#635000
b100110110 7
1!
#636000
0!
#637000
b100110111 7
1!
#638000
0!
#639000
b100111000 7
1!
#640000
0!
#641000
b100111001 7
1!
#642000
0!
#643000
b100111010 7
1!
#644000
0!
#645000
b100111011 7
1!
#646000
0!
#647000
b100111100 7
1!
#648000
0!
#649000
b100111101 7
1!
#650000
0!
#651000
b100111110 7
1!
#652000
0!
#653000
b100111111 7
1!
#654000
0!
#655000
b101000000 7
1!
#656000
0!
#657000
b101000001 7
1!
#658000
0!
#659000
b101000010 7
1!
#660000
0!
#661000
b101000011 7
1!
#662000
0!
#663000
b101000100 7
1!
#664000
0!
#665000
b101000101 7
1!
#666000
0!
#667000
b101000110 7
1!
#668000
0!
#669000
b101000111 7
1!
#670000
0!
#671000
b101001000 7
1!
#672000
0!
#673000
b101001001 7
1!
#674000
0!
#675000
b101001010 7
1!
#676000
0!
#677000
b101001011 7
1!
#678000
0!
#679000
b101001100 7
1!
#680000
0!
#681000
b101001101 7
1!
#682000
0!
#683000
b101001110 7
1!
#684000
0!
#685000
b101001111 7
1!
#686000
0!
#687000
b101010000 7
1!
#688000
0!
#689000
b101010001 7
1!
#690000
0!
#691000
b101010010 7
1!
#692000
0!
#693000
b101010011 7
1!
#694000
0!
#695000
b101010100 7
1!
#696000
0!
#697000
b101010101 7
1!
#698000
0!
#699000
b101010110 7
1!
#700000
0!
#701000
b101010111 7
1!
#702000
0!
#703000
b101011000 7
1!
#704000
0!
#705000
b101011001 7
1!
#706000
0!
#707000
b101011010 7
1!
#708000
0!
#709000
b101011011 7
1!
#710000
0!
#711000
b101011100 7
1!
#712000
0!
#713000
b101011101 7
1!
#714000
0!
#715000
b101011110 7
1!
#716000
0!
#717000
b101011111 7
1!
#718000
0!
#719000
b101100000 7
1!
#720000
0!
#721000
b101100001 7
1!
#722000
0!
#723000
b101100010 7
1!
#724000
0!
#725000
b101100011 7
1!
#726000
0!
#727000
b101100100 7
1!
#728000
0!
#729000
b101100101 7
1!
#730000
0!
#731000
b101100110 7
1!
#732000
0!
#733000
b101100111 7
1!
#734000
0!
#735000
b101101000 7
1!
#736000
0!
#737000
b101101001 7
1!
#738000
0!
#739000
b101101010 7
1!
#740000
0!
#741000
b101101011 7
1!
#742000
0!
#743000
b101101100 7
1!
#744000
0!
#745000
b101101101 7
1!
#746000
0!
#747000
b101101110 7
1!
#748000
0!
#749000
b101101111 7
1!
#750000
0!
#751000
b101110000 7
1!
#752000
0!
#753000
b101110001 7
1!
#754000
0!
#755000
b101110010 7
1!
#756000
0!
#757000
b101110011 7
1!
#758000
0!
#759000
b101110100 7
1!
#760000
0!
#761000
b101110101 7
1!
#762000
0!
#763000
b101110110 7
1!
#764000
0!
#765000
b101110111 7
1!
#766000
0!
#767000
b101111000 7
1!
#768000
0!
#769000
b101111001 7
1!
#770000
0!
#771000
b101111010 7
1!
#772000
0!
#773000
b101111011 7
1!
#774000
0!
#775000
b101111100 7
1!
#776000
0!
#777000
b101111101 7
1!
#778000
0!
#779000
b101111110 7
1!
#780000
0!
#781000
b101111111 7
1!
#782000
0!
#783000
b110000000 7
1!
#784000
0!
#785000
b110000001 7
1!
#786000
0!
#787000
b110000010 7
1!
#788000
0!
#789000
b110000011 7
1!
#790000
0!
#791000
b110000100 7
1!
#792000
0!
#793000
b110000101 7
1!
#794000
0!
#795000
b110000110 7
1!
#796000
0!
#797000
b110000111 7
1!
#798000
0!
#799000
b110001000 7
1!
#800000
0!
#801000
b110001001 7
1!
#802000
0!
#803000
b110001010 7
1!
#804000
0!
#805000
b110001011 7
1!
#806000
0!
#807000
b110001100 7
1!
#808000
0!
#809000
b110001101 7
1!
#810000
0!
#811000
b110001110 7
1!
#812000
0!
#813000
b110001111 7
1!
#814000
0!
#815000
b110010000 7
1!
#816000
0!
#817000
b110010001 7
1!
#818000
0!
#819000
b110010010 7
1!
#820000
0!
#821000
b110010011 7
1!
#822000
0!
#823000
b110010100 7
1!
#824000
0!
#825000
b110010101 7
1!
#826000
0!
#827000
b110010110 7
1!
#828000
0!
#829000
b110010111 7
1!
#830000
0!
#831000
b110011000 7
1!
#832000
0!
#833000
b110011001 7
1!
#834000
0!
#835000
b110011010 7
1!
#836000
0!
#837000
b110011011 7
1!
#838000
0!
#839000
b110011100 7
1!
#840000
0!
#841000
b110011101 7
1!
#842000
0!
#843000
b110011110 7
1!
#844000
0!
#845000
b110011111 7
1!
#846000
0!
#847000
b110100000 7
1!
#848000
0!
#849000
b110100001 7
1!
#850000
0!
#851000
b110100010 7
1!
#852000
0!
#853000
b110100011 7
1!
#854000
0!
#855000
b110100100 7
1!
#856000
0!
#857000
b110100101 7
1!
#858000
0!
#859000
b110100110 7
1!
#860000
0!
#861000
b110100111 7
1!
#862000
0!
#863000
b110101000 7
1!
#864000
0!
#865000
b110101001 7
1!
#866000
0!
#867000
b110101010 7
1!
#868000
0!
#869000
b110101011 7
1!
#870000
0!
#871000
b110101100 7
1!
#872000
0!
#873000
b110101101 7
1!
#874000
0!
#875000
b110101110 7
1!
#876000
0!
#877000
b110101111 7
1!
#878000
0!
